demoi123123123123/__init__.py
demoi123123123123-0.1.0.dist-info/WHEEL
demoi123123123123-0.1.0.dist-info/METADATA
demoi123123123123-0.1.0.dist-info/RECORD
