Metadata-Version: 2.1
Name: demoi123123123123
Version: 0.1.0
Summary: 
Author: Evgeny Pistun
Author-email: Evgeny.Pistun@kaspersky.com
Requires-Python: >=3.8,<4.0
Classifier: Programming Language :: Python :: 3
Classifier: Programming Language :: Python :: 3.8
Classifier: Programming Language :: Python :: 3.9
Classifier: Programming Language :: Python :: 3.10
Requires-Dist: Django (>=4.1.1,<5.0.0)
Requires-Dist: pandas (==1.0.0)
